Ecida/__init__.py
ecida-0.0.33.dist-info/METADATA
ecida-0.0.33.dist-info/WHEEL
ecida-0.0.33.dist-info/top_level.txt
ecida-0.0.33.dist-info/RECORD
