Metadata-Version: 2.4
Name: ecida
Version: 0.0.33
Summary: The ECiDA Python SDK to make things easier.
Author-email: Mostafa Hadadian <hadadian@caidel.com>
License-Expression: MIT
Project-URL: homepage, https://gitlab.com/ecida
Classifier: Operating System :: OS Independent
Requires-Python: >=3.0
Requires-Dist: kafka-python
Requires-Dist: mlflow
Requires-Dist: minio
